ubuntu_package_status/__init__.py
ubuntu_package_status/dist-config.yaml
ubuntu_package_status/gke-kernel-config.yaml
ubuntu_package_status/ubuntu_package_status.py
ubuntu_package_status-0.1.4.dist-info/LICENSE
ubuntu_package_status-0.1.4.dist-info/METADATA
ubuntu_package_status-0.1.4.dist-info/WHEEL
ubuntu_package_status-0.1.4.dist-info/entry_points.txt
ubuntu_package_status-0.1.4.dist-info/top_level.txt
ubuntu_package_status-0.1.4.dist-info/RECORD
