Metadata-Version: 2.1
Name: ubuntu-package-status
Version: 0.1.4
Summary: Helpful utility to fetch package version data for specified packages in the ubuntu archive.
Home-page: 
Author: philroche
Author-email: phil.roche@canonical.com
License-File: LICENSE
Requires-Dist: babel
Requires-Dist: click
Requires-Dist: humanize
Requires-Dist: joblib
Requires-Dist: keyring
Requires-Dist: launchpadlib
Requires-Dist: python-debian
Requires-Dist: pytz
Requires-Dist: pyyaml
Requires-Dist: readchar
